MANIFEST.in
readme.rst
setup.py
sequentialGeojson/__init__.py
sequentialGeojson.egg-info/PKG-INFO
sequentialGeojson.egg-info/SOURCES.txt
sequentialGeojson.egg-info/dependency_links.txt
sequentialGeojson.egg-info/not-zip-safe
sequentialGeojson.egg-info/top_level.txt