Metadata-Version: 1.1
Name: sequentialGeojson
Version: 0.2
Summary: A python generator object that provides sequential access to features inside a FeatureCollection of a GeoJson file.
Home-page: https://github.com/scubbx/sequential-geojson
Author: Markus Mayr
Author-email: markusmayr@gmx.net
License: MIT
Keywords: json sequential generator geojson
Platform: UNKNOWN
Classifier: Programming Language :: Python :: 3.2
